picad/__init__.py
picad/base.py
picad/base_tdd.py
picad/kicad.py
picad/layout.py
picad/lists.py
picad/lists_tdd.py
picad/paneliser.py
picad/schematic.py
picad/schematic_tdd.py
picad/sexpr.py
picad/sexpr_tdd.py
picad-0.1.7.dist-info/METADATA
picad-0.1.7.dist-info/WHEEL
picad-0.1.7.dist-info/RECORD
