Metadata-Version: 2.1
Name: picad
Version: 0.1.7
Summary: Python package for reading and writing KiCad 6+ S-expression files, no dependency on KiCad
Home-page: https://github.com/wideopensource/picad
License: MIT
Author: wideopentech
Author-email: fossie@wideoppentech.co.uk
Requires-Python: >=3.8,<4.0
Classifier: License :: OSI Approved :: MIT License
Classifier: Operating System :: OS Independent
Classifier: Programming Language :: Python :: 3
Classifier: Programming Language :: Python :: 3.8
Classifier: Programming Language :: Python :: 3.9
Classifier: Programming Language :: Python :: 3.10
Classifier: Programming Language :: Python :: 3.11
Classifier: Programming Language :: Python :: 3
Project-URL: Repository, https://github.com/wideopensource/picad
